cofense_intelligence/__init__.py
cofense_intelligence/__main__.py
cofense_intelligence/api.py
cofense_intelligence/cli.py
cofense_intelligence/core.py
cofense_intelligence/intelligence.py
cofense_intelligence/metadata.py
cofense_intelligence/output.py
cofense_intelligence/sqlite.py
cofense_intelligence/syslog.py
cofense_intelligence/outputs/CefFileOutput.py
cofense_intelligence/outputs/CsvFileOutput.py
cofense_intelligence/outputs/FileOutput.py
cofense_intelligence/outputs/HttpOutput.py
cofense_intelligence/outputs/JsonFileOutput.py
cofense_intelligence/outputs/StixFileOutput.py
cofense_intelligence/outputs/SyslogOutput.py
cofense_intelligence/outputs/TextFileOutput.py
cofense_intelligence/outputs/__init__.py
cofense_intelligence/templates/integration_template.py-ptl
cofense_intelligence-5.1.13.dist-info/LICENSE
cofense_intelligence-5.1.13.dist-info/METADATA
cofense_intelligence-5.1.13.dist-info/WHEEL
cofense_intelligence-5.1.13.dist-info/entry_points.txt
cofense_intelligence-5.1.13.dist-info/top_level.txt
cofense_intelligence-5.1.13.dist-info/RECORD
