Metadata-Version: 2.1
Name: cofense-intelligence
Version: 5.1.13
Summary: Cofense Intelligence Integration Library
Home-page: https://www.threathq.com/docs/
Author: Cofense Intelligence Solutions Engineering
Author-email: support@cofense.com
License: Proprietary
Keywords: phishing threat intelligence cofense intelligence
Platform: UNKNOWN
Classifier: Development Status :: 4 - Beta
Classifier: Intended Audience :: Information Technology
Classifier: License :: Free To Use But Restricted
Classifier: Programming Language :: Python :: 2.7
Classifier: Programming Language :: Python :: 3.4
Classifier: Programming Language :: Python :: 3.5
Classifier: Programming Language :: Python :: 3.6
Classifier: Topic :: Security
Requires-Dist: requests (>=2.3)
Requires-Dist: defusedxml (>=0.5.0)
Requires-Dist: six (>=1.11.0)
Requires-Dist: jinja2 (>=2.10)
